LICENSE
MANIFEST.in
README.md
README.txt
setup.py
bin/parser
bin/sign_hotfix
bin/upload_design_docs
bin/uploader
certs/ca/habitat_ca_cert.pem
certs/certs/adamgreig.crt
certs/certs/danielrichman.crt
couchdb/designdocs.yml
couchdb/schemas/flight.json
couchdb/schemas/listener_information.json
couchdb/schemas/listener_telemetry.json
couchdb/schemas/payload_configuration.json
couchdb/schemas/payload_telemetry.json
docs/certs.rst
docs/conf.py
docs/configuration.rst
docs/database.rst
docs/filters.rst
docs/habitat.rst
docs/index.rst
docs/installing.rst
docs/intro.rst
docs/ukhas_parser.rst
docs/diagrams/callgraph.png
docs/diagrams/cg_combined.dot
docs/diagrams/cg_combined.png
docs/diagrams/cg_main.dot
docs/diagrams/cg_main.png
docs/diagrams/cg_thread1.dot
docs/diagrams/cg_thread1.png
docs/diagrams/cg_thread2.dot
docs/diagrams/cg_thread2.png
docs/diagrams/cg_thread3.dot
docs/diagrams/cg_thread3.png
docs/diagrams/cg_thread4.dot
docs/diagrams/cg_thread4.png
docs/diagrams/cg_thread5.dot
docs/diagrams/cg_thread5.png
docs/diagrams/cg_threads.dot
docs/diagrams/class_diagram.dia
docs/diagrams/class_diagram.png
docs/diagrams/use_cases.dia
docs/diagrams/use_cases.png
docs/habitat/habitat.rst
docs/habitat/habitat/habitat.filters.rst
docs/habitat/habitat/habitat.loadable_manager.rst
docs/habitat/habitat/habitat.parser.rst
docs/habitat/habitat/habitat.parser_daemon.rst
docs/habitat/habitat/habitat.parser_modules.rst
docs/habitat/habitat/habitat.sensors.rst
docs/habitat/habitat/habitat.uploader.rst
docs/habitat/habitat/habitat.utils.rst
docs/habitat/habitat/habitat.views.rst
docs/habitat/habitat/habitat/habitat.parser_modules.simple_binary_parser.rst
docs/habitat/habitat/habitat/habitat.parser_modules.ukhas_parser.rst
docs/habitat/habitat/habitat/habitat.sensors.base.rst
docs/habitat/habitat/habitat/habitat.sensors.stdtelem.rst
docs/habitat/habitat/habitat/habitat.utils.checksums.rst
docs/habitat/habitat/habitat/habitat.utils.dynamicloader.rst
habitat.egg-info/PKG-INFO
habitat.egg-info/SOURCES.txt
habitat.egg-info/dependency_links.txt
habitat.egg-info/requires.txt
habitat.egg-info/top_level.txt
