Metadata-Version: 1.0
Name: habitat
Version: 0.3.2
Summary: Next Generation High Altitude Balloon Tracking
Home-page: http://habitat.habhub.org/
Author: HABHUB Team
Author-email: root@habhub.org
License: GNU General Public License Version 3
Platform: UNKNOWN
